{
  "type": "pfm:furniture",
  "group": "tables",
  "ingredients": [
    {
      "item": "byg:cypress_planks"
    },
    {
      "item": "byg:cypress_planks"
    },
    {
      "item": "byg:cypress_planks"
    },
    {
      "item": "byg:cypress_planks"
    },
    {
      "item": "byg:cypress_planks"
    },
    {
      "item": "byg:stripped_cypress_log"
    },
    {
      "item": "byg:stripped_cypress_log"
    },
    {
      "item": "byg:stripped_cypress_log"
    }
  ],
  "result": {
    "item": "pfm:stripped_cypress_byg_table_modern_dinner",
    "count": 4
  }
}