{
  "type": "pfm:furniture",
  "group": "bedroom",
  "ingredients": [
    {
      "item": "byg:bulbis_planks"
    },
    {
      "item": "byg:bulbis_planks"
    },
    {
      "item": "byg:bulbis_planks"
    },
    {
      "item": "byg:bulbis_planks"
    },
    {
      "item": "byg:bulbis_planks"
    },
    {
      "item": "byg:bulbis_planks"
    },
    {
      "item": "byg:stripped_bulbis_stem"
    },
    {
      "item": "minecraft:chest"
    }
  ],
  "result": {
    "item": "pfm:stripped_bulbis_byg_classic_nightstand",
    "count": 4
  }
}